helics-3.6.0.dist-info/entry_points.txt
helics-3.6.0.dist-info/RECORD
helics-3.6.0.dist-info/METADATA
helics-3.6.0.dist-info/WHEEL
helics-3.6.0.dist-info/licenses/LICENSE
helics/utils.py
helics/bin.py
helics/_build.py
helics/_version.py
helics/vcredist.py
helics/status_checker.py
helics/__init__.py
helics/cli.py
helics/profile.py
helics/capi.py
helics/install/bin/helics_app
helics/install/bin/helics_recorder
helics/install/bin/helics_connector
helics/install/bin/helics_broker
helics/install/bin/helics_player
helics/install/bin/helics_broker_server
helics/install/share/helics/swig/helics.i
helics/install/share/doc/HELICS/CHANGELOG.md
helics/install/share/doc/HELICS/NOTICE
helics/install/share/doc/HELICS/LICENSE
helics/install/share/doc/HELICS/THIRDPARTY_LICENSES
helics/install/share/doc/HELICS/README.md
helics/install/share/man/man1/helics_broker-term.1
helics/install/share/man/man1/helics_app-source.1
helics/install/share/man/man1/helics_app-echo.1
helics/install/share/man/man1/helics_player.1
helics/install/share/man/man1/helics_app-tracer.1
helics/install/share/man/man1/helics_app.1
helics/install/share/man/man1/helics_app-broker.1
helics/install/share/man/man1/helics_app-player.1
helics/install/share/man/man1/helics_app-clone.1
helics/install/share/man/man1/helics_broker.1
helics/install/share/man/man1/helics_app-recorder.1
helics/install/include/helics/helics98.hpp
helics/install/include/helics/helics_api.h
helics/install/include/helics/helics.h
helics/install/include/helics/cpp98/config.hpp
helics/install/include/helics/cpp98/Endpoint.hpp
helics/install/include/helics/cpp98/helicsExceptions.hpp
helics/install/include/helics/cpp98/MessageFederate.hpp
helics/install/include/helics/cpp98/Filter.hpp
helics/install/include/helics/cpp98/CombinationFederate.hpp
helics/install/include/helics/cpp98/DataBuffer.hpp
helics/install/include/helics/cpp98/Publication.hpp
helics/install/include/helics/cpp98/Translator.hpp
helics/install/include/helics/cpp98/Input.hpp
helics/install/include/helics/cpp98/Federate.hpp
helics/install/include/helics/cpp98/helics.hpp
