Metadata-Version: 2.1
Name: helics
Version: 3.6.0
Summary: Python HELICS bindings
Keywords: helics,co-simulation
Author-Email: GMLC-TDC <helicsdevelopers@helics.org>
License: BSD License
Classifier: Development Status :: 5 - Production/Stable
Classifier: Intended Audience :: Developers
Classifier: License :: OSI Approved :: MIT License
Classifier: Operating System :: Unix
Classifier: Operating System :: POSIX
Classifier: Operating System :: Microsoft :: Windows
Classifier: Programming Language :: Python
Classifier: Programming Language :: Python :: 3
Classifier: Programming Language :: Python :: 3.8
Classifier: Programming Language :: Python :: Implementation :: CPython
Classifier: Programming Language :: Python :: Implementation :: PyPy
Classifier: Topic :: Utilities
Project-URL: Homepage, https://github.com/GMLC-TDC/pyhelics
Project-URL: Discussions, https://github.com/GMLC-TDC/HELICS/discussions
Project-URL: Documentation, https://python.helics.org/
Project-URL: Issue tracker, https://github.com/GMLC-TDC/pyhelics/issues
Project-URL: Source code, https://github.com/GMLC-TDC/pyhelics
Requires-Python: >=3.8
Requires-Dist: cffi>=1.6.0
Requires-Dist: strip-hints
Requires-Dist: click>=8
Requires-Dist: helics_cli_extras==0.0.1; extra == "cli"
Requires-Dist: matplotlib; extra == "cli"
Requires-Dist: pytest; extra == "tests"
Requires-Dist: pytest-ordering; extra == "tests"
Requires-Dist: pytest-cov; extra == "tests"
Requires-Dist: pytest-runner; extra == "tests"
Requires-Dist: build; extra == "dev"
Requires-Dist: pre-commit; extra == "dev"
Requires-Dist: mkdocs; extra == "docs"
Requires-Dist: inari[mkdocs]; extra == "docs"
Requires-Dist: mkdocs-material; extra == "docs"
Requires-Dist: black; extra == "docs"
Requires-Dist: pygments; extra == "docs"
Requires-Dist: pymdown-extensions; extra == "docs"
Provides-Extra: cli
Provides-Extra: tests
Provides-Extra: dev
Provides-Extra: docs
